LICENSE.rst
README.md
setup.py
Input_Armor.egg-info/PKG-INFO
Input_Armor.egg-info/SOURCES.txt
Input_Armor.egg-info/dependency_links.txt
Input_Armor.egg-info/top_level.txt
input_armor/__init__.py
input_armor/main.py