Metadata-Version: 2.1
Name: Input-Armor
Version: 1.1.3
Summary: This library provides protection from SQL-injections, DOM-manipulation (HTML injections), CMD injections, and almost all types of injections.
Home-page: https://github.com/Armen-Jean-Andreasian
Author: Armen-Jean Andreasian
Author-email: armen_andreasian@proton.me
License: BSD
Keywords: security,injection protection,python
Classifier: Topic :: Software Development :: Libraries :: Python Modules
Classifier: Development Status :: 4 - Beta
Requires-Python: >=3.8
License-File: LICENSE.rst
